pycounts_jo/.ipynb_checkpoints/plotting-checkpoint.py
pycounts_jo/.ipynb_checkpoints/pycounts_jo-checkpoint.py
pycounts_jo/__init__.py
pycounts_jo/plotting.py
pycounts_jo/pycounts_jo.py
pycounts_jo-0.1.0.dist-info/LICENSE
pycounts_jo-0.1.0.dist-info/WHEEL
pycounts_jo-0.1.0.dist-info/METADATA
pycounts_jo-0.1.0.dist-info/RECORD
